{
  "name": "Show Desktop Icon",
  "description": "Show Desktop functionality like on Windows\n\nFor Best Experience: Place the icon Far Right\n\nFeatures:\n-Minimize/Restore all the windows\n-Similar Feel Like on Windows(Similar Look,Non Distracting,etc)\n\nForked from https://extensions.gnome.org/extension/4267/show-desktop-applet/",
  "shell-version": [
    "3.34",
    "3.32",
    "3.36",
    "3.38",
    "40",
    "41",
    "42",
    "43"
  ],
  "url": "https://github.com/fyr3-tty/Show-Desktop-Icon",
  "uuid": "show-desktop-icon@pyr3_",
}